[
    {"model": "core.estado", "fields": {"nome": "Acre", "sigla": "AC"}},
    {"model": "core.estado", "fields": {"nome": "Alagoas", "sigla": "AL"}},
    {"model": "core.estado", "fields": {"nome": "Amapá", "sigla": "AP"}},
    {"model": "core.estado", "fields": {"nome": "Amazonas", "sigla": "AM"}},
    {"model": "core.estado", "fields": {"nome": "Bahia", "sigla": "BA"}},
    {"model": "core.estado", "fields": {"nome": "Ceará", "sigla": "CE"}},
    {"model": "core.estado", "fields": {"nome": "Distrito Federal", "sigla": "DF"}},
    {"model": "core.estado", "fields": {"nome": "Espírito Santo", "sigla": "ES"}},
    {"model": "core.estado", "fields": {"nome": "Goiás", "sigla": "GO"}},
    {"model": "core.estado", "fields": {"nome": "Maranhão", "sigla": "MA"}},
    {"model": "core.estado", "fields": {"nome": "Mato Grosso", "sigla": "MT"}},
    {"model": "core.estado", "fields": {"nome": "Mato Grosso do Sul", "sigla": "MS"}},
    {"model": "core.estado", "fields": {"nome": "Minas Gerais", "sigla": "MG"}},
    {"model": "core.estado", "fields": {"nome": "Pará", "sigla": "PA"}},
    {"model": "core.estado", "fields": {"nome": "Paraíba", "sigla": "PB"}},
    {"model": "core.estado", "fields": {"nome": "Paraná", "sigla": "PR"}},
    {"model": "core.estado", "fields": {"nome": "Pernambuco", "sigla": "PE"}},
    {"model": "core.estado", "fields": {"nome": "Piauí", "sigla": "PI"}},
    {"model": "core.estado", "fields": {"nome": "Rio de Janeiro", "sigla": "RJ"}},
    {"model": "core.estado", "fields": {"nome": "Rio Grande do Norte", "sigla": "RN"}},
    {"model": "core.estado", "fields": {"nome": "Rio Grande do Sul", "sigla": "RS"}},
    {"model": "core.estado", "fields": {"nome": "Rondônia", "sigla": "RO"}},
    {"model": "core.estado", "fields": {"nome": "Roraima", "sigla": "RR"}},
    {"model": "core.estado", "fields": {"nome": "Santa Catarina", "sigla": "SC"}},
    {"model": "core.estado", "fields": {"nome": "São Paulo", "sigla": "SP"}},
    {"model": "core.estado", "fields": {"nome": "Sergipe", "sigla": "SE"}},
    {"model": "core.estado", "fields": {"nome": "Tocantins", "sigla": "TO"}}
  ]
  